.testr.conf
AUTHORS
CONTRIBUTING.rst
ChangeLog
HACKING.rst
LICENSE
MANIFEST.in
README.rst
babel.cfg
requirements.txt
setup.cfg
setup.py
test-requirements.txt
tox.ini
devstack/demo.sh
devstack/demo_wrapper.sh
devstack/local.conf.example.aio
devstack/local.conf.example.compute
devstack/local.conf.example.controller
devstack/plugin.sh
devstack/settings
doc/source/conf.py
doc/source/contributing.rst
doc/source/index.rst
doc/source/installation.rst
doc/source/readme.rst
etc/neutron/plugins/ml2/ml2_conf_fortinet.ini
networking_fortinet/LICENSE
networking_fortinet/README.md
networking_fortinet/__init__.py
networking_fortinet/_i18n.py
networking_fortinet.egg-info/PKG-INFO
networking_fortinet.egg-info/SOURCES.txt
networking_fortinet.egg-info/dependency_links.txt
networking_fortinet.egg-info/entry_points.txt
networking_fortinet.egg-info/not-zip-safe
networking_fortinet.egg-info/pbr.json
networking_fortinet.egg-info/requires.txt
networking_fortinet.egg-info/top_level.txt
networking_fortinet/api_client/__init__.py
networking_fortinet/api_client/base.py
networking_fortinet/api_client/client.py
networking_fortinet/api_client/constants.py
networking_fortinet/api_client/eventlet_client.py
networking_fortinet/api_client/eventlet_request.py
networking_fortinet/api_client/exception.py
networking_fortinet/api_client/request.py
networking_fortinet/api_client/templates.py
networking_fortinet/common/__init__.py
networking_fortinet/common/config.py
networking_fortinet/common/constants.py
networking_fortinet/common/resources.py
networking_fortinet/common/singleton.py
networking_fortinet/common/utils.py
networking_fortinet/db/__init__.py
networking_fortinet/db/models.py
networking_fortinet/db/migration/__init__.py
networking_fortinet/db/migration/alembic_migrations/__init__.py
networking_fortinet/db/migration/alembic_migrations/env.py
networking_fortinet/db/migration/alembic_migrations/script.py.mako
networking_fortinet/db/migration/alembic_migrations/versions/38462bfd9dc_fortinet_plugin_database.py
networking_fortinet/db/migration/alembic_migrations/versions/HEAD
networking_fortinet/ml2/__init__.py
networking_fortinet/ml2/mech_fortinet.py
networking_fortinet/services/__init__.py
networking_fortinet/services/firewall/__init__.py
networking_fortinet/services/firewall/fortinet_fwaas_plugin.py
